{
  "resources": [
    {
      "path": "data.csv",
      "name": "data",
      "profile": "tabular-data-resource",
      "scheme": "file",
      "format": "csv",
      "hashing": "md5",
      "encoding": "utf-8",
      "schema": {
        "fields": [
          {
            "name": "Year",
            "type": "integer",
            "title": "Year"
          },
          {
            "name": "Demographic Characteristic",
            "type": "string",
            "constraints": {
              "enum": [
                "Total_Poverty",
                "Male_Poverty",
                "Female_Poverty",
                "White_Alone_Poverty",
                "Black_Alone_Poverty",
                "American_Indian_Alaska_Native_Poverty",
                "Asian_Poverty",
                "Native_Hawaiian_Other_Pacific_Islander_Poverty",
                "Other_Race_Poverty",
                "Two_Or_More_Races_Poverty",
                "Hispanic_Or_Latino_Poverty",
                "White_Alone_Not_Hispanic_Latino_Poverty",
                ""
              ]
            },
            "title": "Demographic Characteristic"
          },
          {
            "name": "Value",
            "type": "number",
            "title": "Value"
          }
        ]
      }
    }
  ],
  "profile": "data-package",
  "name": "1-2-1",
  "title": "Proportion of population living below the national poverty line, by sex and age"
}